{
  "aliases": [
    "connectedthings"
  ],
  "ambiguity_status": "unresolved",
  "buckets": [
    "tool-component",
    "capability"
  ],
  "candidate_definitions": [
    {
      "source_kind": "repo-description",
      "source_repo": "matter-js/matter.js",
      "status": "candidate-context",
      "text": "A complete typescript implementation of the Matter protocol specification (https://buildwithmatter.com). Includes full support for controller, device, commissioning, secure communications, device types, and cluster definitions."
    },
    {
      "source_kind": "source-snippet",
      "source_repo": "matter-js/matter.js",
      "status": "candidate-context",
      "text": "[![license](https://img.shields.io/badge/license-Apache2-green.svg)](https://raw.githubusercontent.com/matter-js/matter.js/master/LICENSE)"
    },
    {
      "source_kind": "repo-description",
      "source_repo": "Luligu/matterbridge",
      "status": "candidate-context",
      "text": "Matterbridge plugin manager for Matter"
    },
    {
      "source_kind": "source-snippet",
      "source_repo": "Luligu/matterbridge",
      "status": "candidate-context",
      "text": "<!-- eslint-disable markdown/no-multiple-h1 -->"
    },
    {
      "source_kind": "repo-description",
      "source_repo": "Luligu/matterbridge-zigbee2mqtt",
      "status": "candidate-context",
      "text": "Matterbridge zigbee2mqtt plugin"
    },
    {
      "source_kind": "source-snippet",
      "source_repo": "Luligu/matterbridge-zigbee2mqtt",
      "status": "candidate-context",
      "text": "[![npm version](https://img.shields.io/npm/v/matterbridge-zigbee2mqtt.svg)](https://www.npmjs.com/package/matterbridge-zigbee2mqtt)"
    }
  ],
  "candidate_glosses": [
    {
      "source_kind": "source-snippet",
      "source_repo": "matter-js/matter.js",
      "status": "candidate",
      "text": "[![license](https://img.shields.io/badge/license-Apache2-green.svg)](https://raw.githubusercontent.com/matter-js/matter.js/master/LICENSE)"
    },
    {
      "source_kind": "source-snippet",
      "source_repo": "Luligu/matterbridge",
      "status": "candidate",
      "text": "<!-- eslint-disable markdown/no-multiple-h1 -->"
    },
    {
      "source_kind": "source-snippet",
      "source_repo": "Luligu/matterbridge-zigbee2mqtt",
      "status": "candidate",
      "text": "[![npm version](https://img.shields.io/npm/v/matterbridge-zigbee2mqtt.svg)](https://www.npmjs.com/package/matterbridge-zigbee2mqtt)"
    }
  ],
  "candidate_related_terms": [],
  "candidate_synonyms": [],
  "canonical_name": "connectedthings",
  "concept_id": "connectedthings",
  "definition_status": "unresolved",
  "evidence": [
    {
      "discovered_via": "repo-topic",
      "observed_at": "2026-05-13T12:58:22.952944+00:00",
      "source_file": null,
      "source_repo": "matter-js/matter.js"
    },
    {
      "discovered_via": "repo-topic",
      "observed_at": "2026-05-14T00:43:26.166349+00:00",
      "source_file": null,
      "source_repo": "matter-js/matter.js"
    },
    {
      "discovered_via": "repo-topic",
      "observed_at": "2026-05-14T00:43:26.166349+00:00",
      "source_file": null,
      "source_repo": "Luligu/matterbridge"
    },
    {
      "discovered_via": "repo-topic",
      "observed_at": "2026-05-14T12:51:33.279454+00:00",
      "source_file": null,
      "source_repo": "matter-js/matter.js"
    },
    {
      "discovered_via": "repo-topic",
      "observed_at": "2026-05-14T18:43:37.154551+00:00",
      "source_file": null,
      "source_repo": "Luligu/matterbridge-zigbee2mqtt"
    },
    {
      "discovered_via": "repo-topic",
      "observed_at": "2026-05-14T18:43:37.154551+00:00",
      "source_file": null,
      "source_repo": "matter-js/matter.js"
    },
    {
      "discovered_via": "repo-topic",
      "observed_at": "2026-05-15T00:40:36.218046+00:00",
      "source_file": null,
      "source_repo": "matter-js/matter.js"
    },
    {
      "discovered_via": "repo-topic",
      "observed_at": "2026-05-15T12:50:28.227991+00:00",
      "source_file": null,
      "source_repo": "matter-js/matter.js"
    },
    {
      "discovered_via": "repo-topic",
      "observed_at": "2026-05-16T00:38:16.846047+00:00",
      "source_file": null,
      "source_repo": "matter-js/matter.js"
    },
    {
      "discovered_via": "repo-topic",
      "observed_at": "2026-05-16T06:55:35.086614+00:00",
      "source_file": null,
      "source_repo": "matter-js/matter.js"
    },
    {
      "discovered_via": "repo-topic",
      "observed_at": "2026-05-16T18:25:29.547854+00:00",
      "source_file": null,
      "source_repo": "matter-js/matter.js"
    },
    {
      "discovered_via": "repo-topic",
      "observed_at": "2026-05-17T07:06:43.204320+00:00",
      "source_file": null,
      "source_repo": "matter-js/matter.js"
    },
    {
      "discovered_via": "repo-topic",
      "observed_at": "2026-05-17T18:28:54.888436+00:00",
      "source_file": null,
      "source_repo": "matter-js/matter.js"
    },
    {
      "discovered_via": "repo-topic",
      "observed_at": "2026-05-18T00:43:20.098172+00:00",
      "source_file": null,
      "source_repo": "matter-js/matter.js"
    },
    {
      "discovered_via": "repo-topic",
      "observed_at": "2026-05-18T18:44:05.166065+00:00",
      "source_file": null,
      "source_repo": "matter-js/matter.js"
    },
    {
      "discovered_via": "repo-topic",
      "observed_at": "2026-05-19T00:44:50.346858+00:00",
      "source_file": null,
      "source_repo": "matter-js/matter.js"
    },
    {
      "discovered_via": "repo-topic",
      "observed_at": "2026-05-19T07:24:07.075826+00:00",
      "source_file": null,
      "source_repo": "matter-js/matter.js"
    },
    {
      "discovered_via": "repo-topic",
      "observed_at": "2026-05-19T13:24:05.041483+00:00",
      "source_file": null,
      "source_repo": "matter-js/matter.js"
    },
    {
      "discovered_via": "repo-topic",
      "observed_at": "2026-05-19T18:44:49.183462+00:00",
      "source_file": null,
      "source_repo": "matter-js/matter.js"
    },
    {
      "discovered_via": "repo-topic",
      "observed_at": "2026-05-20T07:24:31.235161+00:00",
      "source_file": null,
      "source_repo": "matter-js/matter.js"
    },
    {
      "discovered_via": "repo-topic",
      "observed_at": "2026-05-20T18:55:10.976456+00:00",
      "source_file": null,
      "source_repo": "matter-js/matter.js"
    },
    {
      "discovered_via": "repo-topic",
      "observed_at": "2026-05-21T07:28:23.617453+00:00",
      "source_file": null,
      "source_repo": "matter-js/matter.js"
    },
    {
      "discovered_via": "repo-topic",
      "observed_at": "2026-05-22T00:44:15.720901+00:00",
      "source_file": null,
      "source_repo": "matter-js/matter.js"
    }
  ],
  "first_seen_at": "2026-05-13T12:58:22.952944+00:00",
  "gloss_status": "unresolved",
  "last_seen_at": "2026-05-22T00:44:15.720901+00:00",
  "lexical_providers": [
    "datamuse"
  ],
  "lexical_status": "unresolved",
  "possible_senses": [
    {
      "buckets": [
        "tool-component",
        "capability"
      ],
      "label": "connectedthings",
      "sense_id": "connectedthings#sense-1",
      "status": "candidate"
    }
  ],
  "primary_bucket": "tool-component"
}
