{
  "aliases": [
    "consensus"
  ],
  "ambiguity_status": "unresolved",
  "buckets": [
    "tool-component",
    "capability"
  ],
  "candidate_definitions": [
    {
      "source_kind": "repo-description",
      "source_repo": "etcd-io/etcd",
      "status": "candidate-context",
      "text": "Distributed reliable key-value store for the most critical data of a distributed system"
    },
    {
      "source_kind": "source-snippet",
      "source_repo": "etcd-io/etcd",
      "status": "candidate-context",
      "text": "[![Go Report Card](https://goreportcard.com/badge/github.com/etcd-io/etcd?style=flat-square)](https://goreportcard.com/report/github.com/etcd-io/etcd)"
    },
    {
      "source_kind": "repo-description",
      "source_repo": "meta-pytorch/torchft",
      "status": "candidate-context",
      "text": "Fault tolerance for PyTorch (HSDP, LocalSGD, DiLoCo, Streaming DiLoCo)"
    },
    {
      "source_kind": "source-snippet",
      "source_repo": "meta-pytorch/torchft",
      "status": "candidate-context",
      "text": "<p align=\"center\">"
    },
    {
      "source_kind": "repo-description",
      "source_repo": "spacemeshos/go-spacemesh",
      "status": "candidate-context",
      "text": "Go Implementation of the Spacemesh protocol full node. \ud83d\udcbe\u23f0\ud83d\udcaa"
    },
    {
      "source_kind": "source-snippet",
      "source_repo": "spacemeshos/go-spacemesh",
      "status": "candidate-context",
      "text": "[![license](https://img.shields.io/packagist/l/doctrine/orm.svg)](https://github.com/spacemeshos/go-spacemesh/blob/master/LICENSE)"
    },
    {
      "source_kind": "repo-description",
      "source_repo": "databendlabs/openraft",
      "status": "candidate-context",
      "text": "rust raft with improvements"
    },
    {
      "source_kind": "source-snippet",
      "source_repo": "databendlabs/openraft",
      "status": "candidate-context",
      "text": "<div align=\"center\">"
    },
    {
      "source_kind": "repo-description",
      "source_repo": "tendermint/tendermint",
      "status": "candidate-context",
      "text": "\u27c1 Tendermint Core (BFT Consensus) in Go"
    },
    {
      "source_kind": "source-snippet",
      "source_repo": "tendermint/tendermint",
      "status": "candidate-context",
      "text": "_UPDATE: TendermintCore featureset is frozen for LTS, see issue https://github.com/tendermint/tendermint/issues/9972_<br/>"
    },
    {
      "source_kind": "repo-description",
      "source_repo": "rqlite/rqlite",
      "status": "candidate-context",
      "text": "The lightweight, fault-tolerant database built on SQLite. Designed to keep your data highly available with minimal effort."
    },
    {
      "source_kind": "source-snippet",
      "source_repo": "rqlite/rqlite",
      "status": "candidate-context",
      "text": "<picture>"
    },
    {
      "source_kind": "repo-description",
      "source_repo": "PacificBiosciences/ccs",
      "status": "candidate-context",
      "text": "CCS: Generate Highly Accurate Single-Molecule Consensus Reads (HiFi Reads)"
    },
    {
      "source_kind": "source-snippet",
      "source_repo": "PacificBiosciences/ccs",
      "status": "candidate-context",
      "text": "<a href=\"https://ccs.how/\">"
    }
  ],
  "candidate_glosses": [
    {
      "source_kind": "source-snippet",
      "source_repo": "etcd-io/etcd",
      "status": "candidate",
      "text": "[![Go Report Card](https://goreportcard.com/badge/github.com/etcd-io/etcd?style=flat-square)](https://goreportcard.com/report/github.com/etcd-io/etcd)"
    },
    {
      "source_kind": "source-snippet",
      "source_repo": "meta-pytorch/torchft",
      "status": "candidate",
      "text": "<p align=\"center\">"
    },
    {
      "source_kind": "source-snippet",
      "source_repo": "spacemeshos/go-spacemesh",
      "status": "candidate",
      "text": "[![license](https://img.shields.io/packagist/l/doctrine/orm.svg)](https://github.com/spacemeshos/go-spacemesh/blob/master/LICENSE)"
    },
    {
      "source_kind": "source-snippet",
      "source_repo": "databendlabs/openraft",
      "status": "candidate",
      "text": "<div align=\"center\">"
    },
    {
      "source_kind": "source-snippet",
      "source_repo": "tendermint/tendermint",
      "status": "candidate",
      "text": "_UPDATE: TendermintCore featureset is frozen for LTS, see issue https://github.com/tendermint/tendermint/issues/9972_<br/>"
    },
    {
      "source_kind": "source-snippet",
      "source_repo": "rqlite/rqlite",
      "status": "candidate",
      "text": "<picture>"
    },
    {
      "source_kind": "source-snippet",
      "source_repo": "PacificBiosciences/ccs",
      "status": "candidate",
      "text": "<a href=\"https://ccs.how/\">"
    }
  ],
  "candidate_related_terms": [
    {
      "provider": "datamuse",
      "relation": "meaning-like",
      "score": 29997124,
      "status": "candidate",
      "text": "general agreement"
    },
    {
      "provider": "datamuse",
      "relation": "meaning-like",
      "score": 29997123,
      "status": "candidate",
      "text": "majority"
    },
    {
      "provider": "datamuse",
      "relation": "meaning-like",
      "score": 29996618,
      "status": "candidate",
      "text": "concertation"
    },
    {
      "provider": "datamuse",
      "relation": "meaning-like",
      "score": 29993978,
      "status": "candidate",
      "text": "common"
    },
    {
      "provider": "datamuse",
      "relation": "meaning-like",
      "score": 29991401,
      "status": "candidate",
      "text": "concert"
    }
  ],
  "candidate_synonyms": [
    {
      "provider": "datamuse",
      "relation": "synonym",
      "score": 3,
      "status": "candidate",
      "text": "general agreement"
    }
  ],
  "canonical_name": "consensus",
  "concept_id": "consensus",
  "definition_status": "unresolved",
  "evidence": [
    {
      "discovered_via": "repo-topic",
      "observed_at": "2026-04-23T04:27:42.433064+00:00",
      "source_file": null,
      "source_repo": "etcd-io/etcd"
    },
    {
      "discovered_via": "repo-topic",
      "observed_at": "2026-04-23T18:30:35.670459+00:00",
      "source_file": null,
      "source_repo": "etcd-io/etcd"
    },
    {
      "discovered_via": "repo-topic",
      "observed_at": "2026-04-24T06:47:13.899148+00:00",
      "source_file": null,
      "source_repo": "meta-pytorch/torchft"
    },
    {
      "discovered_via": "repo-topic",
      "observed_at": "2026-04-29T18:37:00.726333+00:00",
      "source_file": null,
      "source_repo": "meta-pytorch/torchft"
    },
    {
      "discovered_via": "repo-topic",
      "observed_at": "2026-04-29T18:37:00.726333+00:00",
      "source_file": null,
      "source_repo": "spacemeshos/go-spacemesh"
    },
    {
      "discovered_via": "repo-topic",
      "observed_at": "2026-04-30T00:37:16.824464+00:00",
      "source_file": null,
      "source_repo": "meta-pytorch/torchft"
    },
    {
      "discovered_via": "repo-topic",
      "observed_at": "2026-04-30T07:00:14.271058+00:00",
      "source_file": null,
      "source_repo": "meta-pytorch/torchft"
    },
    {
      "discovered_via": "repo-topic",
      "observed_at": "2026-04-30T12:45:20.475770+00:00",
      "source_file": null,
      "source_repo": "etcd-io/etcd"
    },
    {
      "discovered_via": "repo-topic",
      "observed_at": "2026-04-30T12:45:20.475770+00:00",
      "source_file": null,
      "source_repo": "meta-pytorch/torchft"
    },
    {
      "discovered_via": "repo-topic",
      "observed_at": "2026-05-01T00:40:17.248794+00:00",
      "source_file": null,
      "source_repo": "meta-pytorch/torchft"
    },
    {
      "discovered_via": "repo-topic",
      "observed_at": "2026-05-01T07:02:51.781400+00:00",
      "source_file": null,
      "source_repo": "meta-pytorch/torchft"
    },
    {
      "discovered_via": "repo-topic",
      "observed_at": "2026-05-01T12:32:24.464365+00:00",
      "source_file": null,
      "source_repo": "meta-pytorch/torchft"
    },
    {
      "discovered_via": "repo-topic",
      "observed_at": "2026-05-02T06:47:22.946566+00:00",
      "source_file": null,
      "source_repo": "meta-pytorch/torchft"
    },
    {
      "discovered_via": "repo-topic",
      "observed_at": "2026-05-02T18:23:34.576038+00:00",
      "source_file": null,
      "source_repo": "meta-pytorch/torchft"
    },
    {
      "discovered_via": "repo-topic",
      "observed_at": "2026-05-03T00:38:05.423502+00:00",
      "source_file": null,
      "source_repo": "meta-pytorch/torchft"
    },
    {
      "discovered_via": "repo-topic",
      "observed_at": "2026-05-03T00:38:05.423502+00:00",
      "source_file": null,
      "source_repo": "databendlabs/openraft"
    },
    {
      "discovered_via": "repo-topic",
      "observed_at": "2026-05-03T06:58:35.245846+00:00",
      "source_file": null,
      "source_repo": "meta-pytorch/torchft"
    },
    {
      "discovered_via": "repo-topic",
      "observed_at": "2026-05-03T12:28:59.064965+00:00",
      "source_file": null,
      "source_repo": "tendermint/tendermint"
    },
    {
      "discovered_via": "repo-topic",
      "observed_at": "2026-05-03T12:28:59.064965+00:00",
      "source_file": null,
      "source_repo": "meta-pytorch/torchft"
    },
    {
      "discovered_via": "repo-topic",
      "observed_at": "2026-05-03T18:24:01.791245+00:00",
      "source_file": null,
      "source_repo": "databendlabs/openraft"
    },
    {
      "discovered_via": "repo-topic",
      "observed_at": "2026-05-03T18:24:01.791245+00:00",
      "source_file": null,
      "source_repo": "meta-pytorch/torchft"
    },
    {
      "discovered_via": "repo-topic",
      "observed_at": "2026-05-03T18:24:01.791245+00:00",
      "source_file": null,
      "source_repo": "rqlite/rqlite"
    },
    {
      "discovered_via": "repo-topic",
      "observed_at": "2026-05-04T07:12:05.012081+00:00",
      "source_file": null,
      "source_repo": "meta-pytorch/torchft"
    },
    {
      "discovered_via": "repo-topic",
      "observed_at": "2026-05-04T18:39:47.264597+00:00",
      "source_file": null,
      "source_repo": "meta-pytorch/torchft"
    },
    {
      "discovered_via": "repo-topic",
      "observed_at": "2026-05-05T00:36:37.683079+00:00",
      "source_file": null,
      "source_repo": "meta-pytorch/torchft"
    },
    {
      "discovered_via": "repo-topic",
      "observed_at": "2026-05-05T12:38:52.093380+00:00",
      "source_file": null,
      "source_repo": "meta-pytorch/torchft"
    },
    {
      "discovered_via": "repo-topic",
      "observed_at": "2026-05-05T12:38:52.093380+00:00",
      "source_file": null,
      "source_repo": "PacificBiosciences/ccs"
    },
    {
      "discovered_via": "repo-topic",
      "observed_at": "2026-05-05T18:38:09.351693+00:00",
      "source_file": null,
      "source_repo": "etcd-io/etcd"
    },
    {
      "discovered_via": "repo-topic",
      "observed_at": "2026-05-05T18:38:09.351693+00:00",
      "source_file": null,
      "source_repo": "meta-pytorch/torchft"
    },
    {
      "discovered_via": "repo-topic",
      "observed_at": "2026-05-06T12:51:12.481137+00:00",
      "source_file": null,
      "source_repo": "meta-pytorch/torchft"
    },
    {
      "discovered_via": "repo-topic",
      "observed_at": "2026-05-07T00:37:24.413591+00:00",
      "source_file": null,
      "source_repo": "meta-pytorch/torchft"
    },
    {
      "discovered_via": "repo-topic",
      "observed_at": "2026-05-07T07:09:11.945528+00:00",
      "source_file": null,
      "source_repo": "meta-pytorch/torchft"
    },
    {
      "discovered_via": "repo-topic",
      "observed_at": "2026-05-07T12:51:40.300011+00:00",
      "source_file": null,
      "source_repo": "meta-pytorch/torchft"
    },
    {
      "discovered_via": "repo-topic",
      "observed_at": "2026-05-08T00:38:13.543216+00:00",
      "source_file": null,
      "source_repo": "meta-pytorch/torchft"
    },
    {
      "discovered_via": "repo-topic",
      "observed_at": "2026-05-08T12:43:50.373126+00:00",
      "source_file": null,
      "source_repo": "meta-pytorch/torchft"
    },
    {
      "discovered_via": "repo-topic",
      "observed_at": "2026-05-09T00:39:13.791861+00:00",
      "source_file": null,
      "source_repo": "meta-pytorch/torchft"
    },
    {
      "discovered_via": "repo-topic",
      "observed_at": "2026-05-09T06:51:24.890752+00:00",
      "source_file": null,
      "source_repo": "meta-pytorch/torchft"
    },
    {
      "discovered_via": "repo-topic",
      "observed_at": "2026-05-09T12:31:19.030154+00:00",
      "source_file": null,
      "source_repo": "meta-pytorch/torchft"
    },
    {
      "discovered_via": "repo-topic",
      "observed_at": "2026-05-09T18:25:38.031362+00:00",
      "source_file": null,
      "source_repo": "meta-pytorch/torchft"
    },
    {
      "discovered_via": "repo-topic",
      "observed_at": "2026-05-10T00:39:41.381728+00:00",
      "source_file": null,
      "source_repo": "meta-pytorch/torchft"
    },
    {
      "discovered_via": "repo-topic",
      "observed_at": "2026-05-10T07:03:13.220143+00:00",
      "source_file": null,
      "source_repo": "meta-pytorch/torchft"
    },
    {
      "discovered_via": "repo-topic",
      "observed_at": "2026-05-10T18:25:41.670160+00:00",
      "source_file": null,
      "source_repo": "meta-pytorch/torchft"
    },
    {
      "discovered_via": "repo-topic",
      "observed_at": "2026-05-11T00:40:20.012502+00:00",
      "source_file": null,
      "source_repo": "meta-pytorch/torchft"
    },
    {
      "discovered_via": "repo-topic",
      "observed_at": "2026-05-11T13:15:38.721392+00:00",
      "source_file": null,
      "source_repo": "meta-pytorch/torchft"
    },
    {
      "discovered_via": "repo-topic",
      "observed_at": "2026-05-11T18:44:26.583561+00:00",
      "source_file": null,
      "source_repo": "meta-pytorch/torchft"
    },
    {
      "discovered_via": "repo-topic",
      "observed_at": "2026-05-12T00:37:36.884355+00:00",
      "source_file": null,
      "source_repo": "meta-pytorch/torchft"
    },
    {
      "discovered_via": "repo-topic",
      "observed_at": "2026-05-12T18:45:33.862672+00:00",
      "source_file": null,
      "source_repo": "meta-pytorch/torchft"
    },
    {
      "discovered_via": "repo-topic",
      "observed_at": "2026-05-13T00:41:47.952744+00:00",
      "source_file": null,
      "source_repo": "meta-pytorch/torchft"
    },
    {
      "discovered_via": "repo-topic",
      "observed_at": "2026-05-13T07:12:28.410129+00:00",
      "source_file": null,
      "source_repo": "meta-pytorch/torchft"
    },
    {
      "discovered_via": "repo-topic",
      "observed_at": "2026-05-13T12:58:22.952944+00:00",
      "source_file": null,
      "source_repo": "meta-pytorch/torchft"
    },
    {
      "discovered_via": "repo-topic",
      "observed_at": "2026-05-14T00:43:26.166349+00:00",
      "source_file": null,
      "source_repo": "meta-pytorch/torchft"
    },
    {
      "discovered_via": "repo-topic",
      "observed_at": "2026-05-14T12:51:33.279454+00:00",
      "source_file": null,
      "source_repo": "meta-pytorch/torchft"
    },
    {
      "discovered_via": "repo-topic",
      "observed_at": "2026-05-14T18:43:37.154551+00:00",
      "source_file": null,
      "source_repo": "meta-pytorch/torchft"
    },
    {
      "discovered_via": "repo-topic",
      "observed_at": "2026-05-15T00:40:36.218046+00:00",
      "source_file": null,
      "source_repo": "meta-pytorch/torchft"
    },
    {
      "discovered_via": "repo-topic",
      "observed_at": "2026-05-15T12:50:28.227991+00:00",
      "source_file": null,
      "source_repo": "meta-pytorch/torchft"
    },
    {
      "discovered_via": "repo-topic",
      "observed_at": "2026-05-15T18:39:58.785167+00:00",
      "source_file": null,
      "source_repo": "meta-pytorch/torchft"
    },
    {
      "discovered_via": "repo-topic",
      "observed_at": "2026-05-16T00:38:16.846047+00:00",
      "source_file": null,
      "source_repo": "meta-pytorch/torchft"
    },
    {
      "discovered_via": "repo-topic",
      "observed_at": "2026-05-16T06:55:35.086614+00:00",
      "source_file": null,
      "source_repo": "meta-pytorch/torchft"
    },
    {
      "discovered_via": "repo-topic",
      "observed_at": "2026-05-16T18:25:29.547854+00:00",
      "source_file": null,
      "source_repo": "meta-pytorch/torchft"
    },
    {
      "discovered_via": "repo-topic",
      "observed_at": "2026-05-17T07:06:43.204320+00:00",
      "source_file": null,
      "source_repo": "meta-pytorch/torchft"
    },
    {
      "discovered_via": "repo-topic",
      "observed_at": "2026-05-17T18:28:54.888436+00:00",
      "source_file": null,
      "source_repo": "meta-pytorch/torchft"
    },
    {
      "discovered_via": "repo-topic",
      "observed_at": "2026-05-18T07:35:35.489189+00:00",
      "source_file": null,
      "source_repo": "meta-pytorch/torchft"
    },
    {
      "discovered_via": "repo-topic",
      "observed_at": "2026-05-18T18:44:05.166065+00:00",
      "source_file": null,
      "source_repo": "meta-pytorch/torchft"
    },
    {
      "discovered_via": "repo-topic",
      "observed_at": "2026-05-19T00:44:50.346858+00:00",
      "source_file": null,
      "source_repo": "meta-pytorch/torchft"
    },
    {
      "discovered_via": "repo-topic",
      "observed_at": "2026-05-19T07:24:07.075826+00:00",
      "source_file": null,
      "source_repo": "meta-pytorch/torchft"
    },
    {
      "discovered_via": "repo-topic",
      "observed_at": "2026-05-19T13:24:05.041483+00:00",
      "source_file": null,
      "source_repo": "meta-pytorch/torchft"
    },
    {
      "discovered_via": "repo-topic",
      "observed_at": "2026-05-20T00:46:08.525261+00:00",
      "source_file": null,
      "source_repo": "meta-pytorch/torchft"
    },
    {
      "discovered_via": "repo-topic",
      "observed_at": "2026-05-20T07:24:31.235161+00:00",
      "source_file": null,
      "source_repo": "meta-pytorch/torchft"
    },
    {
      "discovered_via": "repo-topic",
      "observed_at": "2026-05-20T18:55:10.976456+00:00",
      "source_file": null,
      "source_repo": "meta-pytorch/torchft"
    },
    {
      "discovered_via": "repo-topic",
      "observed_at": "2026-05-21T07:28:23.617453+00:00",
      "source_file": null,
      "source_repo": "meta-pytorch/torchft"
    },
    {
      "discovered_via": "repo-topic",
      "observed_at": "2026-05-21T18:45:28.518020+00:00",
      "source_file": null,
      "source_repo": "meta-pytorch/torchft"
    },
    {
      "discovered_via": "repo-topic",
      "observed_at": "2026-05-22T00:44:15.720901+00:00",
      "source_file": null,
      "source_repo": "meta-pytorch/torchft"
    },
    {
      "discovered_via": "repo-topic",
      "observed_at": "2026-05-22T07:24:26.652079+00:00",
      "source_file": null,
      "source_repo": "meta-pytorch/torchft"
    },
    {
      "discovered_via": "repo-topic",
      "observed_at": "2026-05-22T13:06:06.618387+00:00",
      "source_file": null,
      "source_repo": "meta-pytorch/torchft"
    },
    {
      "discovered_via": "repo-topic",
      "observed_at": "2026-05-22T18:43:38.426013+00:00",
      "source_file": null,
      "source_repo": "meta-pytorch/torchft"
    },
    {
      "discovered_via": "repo-topic",
      "observed_at": "2026-05-23T00:43:18.102458+00:00",
      "source_file": null,
      "source_repo": "meta-pytorch/torchft"
    },
    {
      "discovered_via": "repo-topic",
      "observed_at": "2026-05-24T00:44:26.398961+00:00",
      "source_file": null,
      "source_repo": "meta-pytorch/torchft"
    },
    {
      "discovered_via": "repo-topic",
      "observed_at": "2026-05-24T07:15:32.140894+00:00",
      "source_file": null,
      "source_repo": "meta-pytorch/torchft"
    },
    {
      "discovered_via": "repo-topic",
      "observed_at": "2026-05-24T18:29:15.298835+00:00",
      "source_file": null,
      "source_repo": "meta-pytorch/torchft"
    },
    {
      "discovered_via": "repo-topic",
      "observed_at": "2026-05-25T07:45:58.058620+00:00",
      "source_file": null,
      "source_repo": "meta-pytorch/torchft"
    },
    {
      "discovered_via": "repo-topic",
      "observed_at": "2026-05-25T13:24:13.030254+00:00",
      "source_file": null,
      "source_repo": "meta-pytorch/torchft"
    },
    {
      "discovered_via": "repo-topic",
      "observed_at": "2026-05-25T18:41:09.248128+00:00",
      "source_file": null,
      "source_repo": "meta-pytorch/torchft"
    },
    {
      "discovered_via": "repo-topic",
      "observed_at": "2026-05-26T07:24:03.857926+00:00",
      "source_file": null,
      "source_repo": "meta-pytorch/torchft"
    },
    {
      "discovered_via": "repo-topic",
      "observed_at": "2026-05-26T13:17:40.210760+00:00",
      "source_file": null,
      "source_repo": "meta-pytorch/torchft"
    },
    {
      "discovered_via": "repo-topic",
      "observed_at": "2026-05-26T18:56:15.123228+00:00",
      "source_file": null,
      "source_repo": "meta-pytorch/torchft"
    },
    {
      "discovered_via": "repo-topic",
      "observed_at": "2026-05-30T00:44:22.415230+00:00",
      "source_file": null,
      "source_repo": "meta-pytorch/torchft"
    },
    {
      "discovered_via": "repo-topic",
      "observed_at": "2026-06-21T19:22:13.525033+00:00",
      "source_file": null,
      "source_repo": "meta-pytorch/torchft"
    },
    {
      "discovered_via": "repo-topic",
      "observed_at": "2026-06-22T08:16:23.314074+00:00",
      "source_file": null,
      "source_repo": "meta-pytorch/torchft"
    },
    {
      "discovered_via": "repo-topic",
      "observed_at": "2026-06-22T14:08:32.759567+00:00",
      "source_file": null,
      "source_repo": "meta-pytorch/torchft"
    },
    {
      "discovered_via": "repo-topic",
      "observed_at": "2026-06-23T00:47:09.772172+00:00",
      "source_file": null,
      "source_repo": "meta-pytorch/torchft"
    },
    {
      "discovered_via": "repo-topic",
      "observed_at": "2026-06-23T13:14:02.543868+00:00",
      "source_file": null,
      "source_repo": "meta-pytorch/torchft"
    },
    {
      "discovered_via": "repo-topic",
      "observed_at": "2026-06-23T18:51:00.487200+00:00",
      "source_file": null,
      "source_repo": "meta-pytorch/torchft"
    },
    {
      "discovered_via": "repo-topic",
      "observed_at": "2026-06-24T13:00:17.759930+00:00",
      "source_file": null,
      "source_repo": "meta-pytorch/torchft"
    },
    {
      "discovered_via": "repo-topic",
      "observed_at": "2026-06-25T00:47:33.944341+00:00",
      "source_file": null,
      "source_repo": "meta-pytorch/torchft"
    },
    {
      "discovered_via": "repo-topic",
      "observed_at": "2026-06-25T13:00:34.017104+00:00",
      "source_file": null,
      "source_repo": "meta-pytorch/torchft"
    }
  ],
  "first_seen_at": "2026-04-23T04:27:42.433064+00:00",
  "gloss_status": "unresolved",
  "last_seen_at": "2026-06-25T13:00:34.017104+00:00",
  "lexical_providers": [
    "datamuse"
  ],
  "lexical_status": "unresolved",
  "possible_senses": [
    {
      "buckets": [
        "tool-component",
        "capability"
      ],
      "label": "consensus",
      "sense_id": "consensus#sense-1",
      "status": "candidate"
    }
  ],
  "primary_bucket": "tool-component"
}
