{
  "components": [
    {
      "component": "eslint",
      "edge_type": "package-json:devDependencies",
      "source_file": "package.json"
    },
    {
      "component": "actions/checkout@v3",
      "edge_type": "workflow-uses",
      "source_file": ".github/workflows/on_pull_request.yaml"
    },
    {
      "component": "actions/setup-python@v4",
      "edge_type": "workflow-uses",
      "source_file": ".github/workflows/on_pull_request.yaml"
    },
    {
      "component": "actions/checkout@v3",
      "edge_type": "workflow-uses",
      "source_file": ".github/workflows/on_pull_request.yaml"
    },
    {
      "component": "actions/setup-node@v3",
      "edge_type": "workflow-uses",
      "source_file": ".github/workflows/on_pull_request.yaml"
    },
    {
      "component": "actions/checkout@v3",
      "edge_type": "workflow-uses",
      "source_file": ".github/workflows/run_tests.yaml"
    },
    {
      "component": "actions/setup-python@v4",
      "edge_type": "workflow-uses",
      "source_file": ".github/workflows/run_tests.yaml"
    },
    {
      "component": "actions/upload-artifact@v3",
      "edge_type": "workflow-uses",
      "source_file": ".github/workflows/run_tests.yaml"
    },
    {
      "component": "actions/upload-artifact@v3",
      "edge_type": "workflow-uses",
      "source_file": ".github/workflows/run_tests.yaml"
    }
  ],
  "edges": [
    {
      "edge_type": "explicit-github-link",
      "source_file": "README.md",
      "source_repo": "openvinotoolkit/stable-diffusion-webui",
      "target": "mv-lab/swin2sr",
      "target_type": "repository"
    },
    {
      "edge_type": "explicit-github-link",
      "source_file": "README.md",
      "source_repo": "openvinotoolkit/stable-diffusion-webui",
      "target": "parlance-zz/g-diffuser-bot",
      "target_type": "repository"
    },
    {
      "edge_type": "explicit-github-link",
      "source_file": "README.md",
      "source_repo": "openvinotoolkit/stable-diffusion-webui",
      "target": "pharmapsychotic/clip-interrogator",
      "target_type": "repository"
    },
    {
      "edge_type": "explicit-github-link",
      "source_file": "README.md",
      "source_repo": "openvinotoolkit/stable-diffusion-webui",
      "target": "newbeeer/diffusion_restart_sampling",
      "target_type": "repository"
    },
    {
      "edge_type": "package-json:devDependencies",
      "source_file": "package.json",
      "source_repo": "openvinotoolkit/stable-diffusion-webui",
      "target": "eslint",
      "target_type": "component"
    },
    {
      "edge_type": "workflow-uses",
      "source_file": ".github/workflows/on_pull_request.yaml",
      "source_repo": "openvinotoolkit/stable-diffusion-webui",
      "target": "actions/checkout@v3",
      "target_type": "component"
    },
    {
      "edge_type": "workflow-uses",
      "source_file": ".github/workflows/on_pull_request.yaml",
      "source_repo": "openvinotoolkit/stable-diffusion-webui",
      "target": "actions/setup-python@v4",
      "target_type": "component"
    },
    {
      "edge_type": "workflow-uses",
      "source_file": ".github/workflows/on_pull_request.yaml",
      "source_repo": "openvinotoolkit/stable-diffusion-webui",
      "target": "actions/setup-node@v3",
      "target_type": "component"
    },
    {
      "edge_type": "workflow-name",
      "source_file": ".github/workflows/on_pull_request.yaml",
      "source_repo": "openvinotoolkit/stable-diffusion-webui",
      "target": "Linter",
      "target_type": "term"
    },
    {
      "edge_type": "workflow-uses",
      "source_file": ".github/workflows/run_tests.yaml",
      "source_repo": "openvinotoolkit/stable-diffusion-webui",
      "target": "actions/checkout@v3",
      "target_type": "component"
    },
    {
      "edge_type": "workflow-uses",
      "source_file": ".github/workflows/run_tests.yaml",
      "source_repo": "openvinotoolkit/stable-diffusion-webui",
      "target": "actions/setup-python@v4",
      "target_type": "component"
    },
    {
      "edge_type": "workflow-uses",
      "source_file": ".github/workflows/run_tests.yaml",
      "source_repo": "openvinotoolkit/stable-diffusion-webui",
      "target": "actions/upload-artifact@v3",
      "target_type": "component"
    },
    {
      "edge_type": "workflow-name",
      "source_file": ".github/workflows/run_tests.yaml",
      "source_repo": "openvinotoolkit/stable-diffusion-webui",
      "target": "Tests",
      "target_type": "term"
    },
    {
      "edge_type": "workflow-name",
      "source_file": ".github/workflows/warns_merge_master.yml",
      "source_repo": "openvinotoolkit/stable-diffusion-webui",
      "target": "Pull requests can't target master branch",
      "target_type": "term"
    }
  ],
  "fetched_at": "2026-04-29T21:51:12.254885+00:00",
  "fetched_files": [
    {
      "path": "README.md",
      "size": 12401
    },
    {
      "path": "package.json",
      "size": 185
    },
    {
      "path": "pyproject.toml",
      "size": 763
    },
    {
      "path": "requirements.txt",
      "size": 396
    },
    {
      "path": ".github/workflows/on_pull_request.yaml",
      "size": 1233
    },
    {
      "path": ".github/workflows/run_tests.yaml",
      "size": 2319
    },
    {
      "path": ".github/workflows/warns_merge_master.yml",
      "size": 424
    }
  ],
  "related_repositories": [],
  "repo": {
    "archived": false,
    "default_branch": "master",
    "description": "Stable Diffusion web UI",
    "fork": true,
    "full_name": "openvinotoolkit/stable-diffusion-webui",
    "html_url": "https://github.com/openvinotoolkit/stable-diffusion-webui",
    "language": "Python",
    "pushed_at": "2024-06-26T23:27:29Z",
    "stargazers_count": 348,
    "topics": [],
    "updated_at": "2026-04-27T11:19:02Z"
  },
  "repo_links": [
    {
      "edge_type": "explicit-github-link",
      "full_name": "mv-lab/swin2sr",
      "source_file": "README.md"
    },
    {
      "edge_type": "explicit-github-link",
      "full_name": "newbeeer/diffusion_restart_sampling",
      "source_file": "README.md"
    },
    {
      "edge_type": "explicit-github-link",
      "full_name": "parlance-zz/g-diffuser-bot",
      "source_file": "README.md"
    },
    {
      "edge_type": "explicit-github-link",
      "full_name": "pharmapsychotic/clip-interrogator",
      "source_file": "README.md"
    }
  ],
  "terms": [
    {
      "context_snippet": "Linter",
      "edge_type": "workflow-name",
      "source_file": ".github/workflows/on_pull_request.yaml",
      "term": "Linter"
    },
    {
      "context_snippet": "Tests",
      "edge_type": "workflow-name",
      "source_file": ".github/workflows/run_tests.yaml",
      "term": "Tests"
    },
    {
      "context_snippet": "Pull requests can't target master branch",
      "edge_type": "workflow-name",
      "source_file": ".github/workflows/warns_merge_master.yml",
      "term": "Pull requests can't target master branch"
    }
  ]
}
