{
  "components": [
    {
      "component": "actions/checkout@v3",
      "edge_type": "workflow-uses",
      "source_file": ".github/workflows/build.yml"
    },
    {
      "component": "simplex-chat/release-changelog-builder-action@v5",
      "edge_type": "workflow-uses",
      "source_file": ".github/workflows/build.yml"
    },
    {
      "component": "simplex-chat/action-gh-release@v2",
      "edge_type": "workflow-uses",
      "source_file": ".github/workflows/build.yml"
    },
    {
      "component": "actions/checkout@v3",
      "edge_type": "workflow-uses",
      "source_file": ".github/workflows/build.yml"
    },
    {
      "component": "simplex-chat/docker-setup-buildx-action@v3",
      "edge_type": "workflow-uses",
      "source_file": ".github/workflows/build.yml"
    },
    {
      "component": "simplex-chat/docker-build-push-action@v6",
      "edge_type": "workflow-uses",
      "source_file": ".github/workflows/build.yml"
    },
    {
      "component": "actions/cache@v4",
      "edge_type": "workflow-uses",
      "source_file": ".github/workflows/build.yml"
    },
    {
      "component": "simplex-chat/action-gh-release@v2",
      "edge_type": "workflow-uses",
      "source_file": ".github/workflows/build.yml"
    },
    {
      "component": "actions/checkout@v4",
      "edge_type": "workflow-uses",
      "source_file": ".github/workflows/docker-image.yml"
    },
    {
      "component": "simplex-chat/docker-login-action@v3",
      "edge_type": "workflow-uses",
      "source_file": ".github/workflows/docker-image.yml"
    },
    {
      "component": "simplex-chat/docker-metadata-action@v5",
      "edge_type": "workflow-uses",
      "source_file": ".github/workflows/docker-image.yml"
    },
    {
      "component": "docker/setup-qemu-action@v3",
      "edge_type": "workflow-uses",
      "source_file": ".github/workflows/docker-image.yml"
    },
    {
      "component": "docker/setup-buildx-action@v3",
      "edge_type": "workflow-uses",
      "source_file": ".github/workflows/docker-image.yml"
    },
    {
      "component": "simplex-chat/docker-build-push-action@v6",
      "edge_type": "workflow-uses",
      "source_file": ".github/workflows/docker-image.yml"
    },
    {
      "component": "actions/checkout@v3",
      "edge_type": "workflow-uses",
      "source_file": ".github/workflows/reproduce-schedule.yml"
    }
  ],
  "edges": [
    {
      "edge_type": "explicit-github-link",
      "source_file": "Dockerfile",
      "source_repo": "simplex-chat/simplexmq",
      "target": "mshekow/directory-checksum",
      "target_type": "repository"
    },
    {
      "edge_type": "workflow-uses",
      "source_file": ".github/workflows/build.yml",
      "source_repo": "simplex-chat/simplexmq",
      "target": "actions/checkout@v3",
      "target_type": "component"
    },
    {
      "edge_type": "workflow-uses",
      "source_file": ".github/workflows/build.yml",
      "source_repo": "simplex-chat/simplexmq",
      "target": "simplex-chat/release-changelog-builder-action@v5",
      "target_type": "component"
    },
    {
      "edge_type": "workflow-uses",
      "source_file": ".github/workflows/build.yml",
      "source_repo": "simplex-chat/simplexmq",
      "target": "simplex-chat/action-gh-release@v2",
      "target_type": "component"
    },
    {
      "edge_type": "workflow-uses",
      "source_file": ".github/workflows/build.yml",
      "source_repo": "simplex-chat/simplexmq",
      "target": "simplex-chat/docker-setup-buildx-action@v3",
      "target_type": "component"
    },
    {
      "edge_type": "workflow-uses",
      "source_file": ".github/workflows/build.yml",
      "source_repo": "simplex-chat/simplexmq",
      "target": "simplex-chat/docker-build-push-action@v6",
      "target_type": "component"
    },
    {
      "edge_type": "workflow-uses",
      "source_file": ".github/workflows/build.yml",
      "source_repo": "simplex-chat/simplexmq",
      "target": "actions/cache@v4",
      "target_type": "component"
    },
    {
      "edge_type": "workflow-name",
      "source_file": ".github/workflows/build.yml",
      "source_repo": "simplex-chat/simplexmq",
      "target": "build",
      "target_type": "term"
    },
    {
      "edge_type": "workflow-uses",
      "source_file": ".github/workflows/docker-image.yml",
      "source_repo": "simplex-chat/simplexmq",
      "target": "actions/checkout@v4",
      "target_type": "component"
    },
    {
      "edge_type": "workflow-uses",
      "source_file": ".github/workflows/docker-image.yml",
      "source_repo": "simplex-chat/simplexmq",
      "target": "simplex-chat/docker-login-action@v3",
      "target_type": "component"
    },
    {
      "edge_type": "workflow-uses",
      "source_file": ".github/workflows/docker-image.yml",
      "source_repo": "simplex-chat/simplexmq",
      "target": "simplex-chat/docker-metadata-action@v5",
      "target_type": "component"
    },
    {
      "edge_type": "workflow-uses",
      "source_file": ".github/workflows/docker-image.yml",
      "source_repo": "simplex-chat/simplexmq",
      "target": "docker/setup-qemu-action@v3",
      "target_type": "component"
    },
    {
      "edge_type": "workflow-uses",
      "source_file": ".github/workflows/docker-image.yml",
      "source_repo": "simplex-chat/simplexmq",
      "target": "docker/setup-buildx-action@v3",
      "target_type": "component"
    },
    {
      "edge_type": "workflow-uses",
      "source_file": ".github/workflows/docker-image.yml",
      "source_repo": "simplex-chat/simplexmq",
      "target": "simplex-chat/docker-build-push-action@v6",
      "target_type": "component"
    },
    {
      "edge_type": "workflow-uses",
      "source_file": ".github/workflows/reproduce-schedule.yml",
      "source_repo": "simplex-chat/simplexmq",
      "target": "actions/checkout@v3",
      "target_type": "component"
    },
    {
      "edge_type": "workflow-name",
      "source_file": ".github/workflows/reproduce-schedule.yml",
      "source_repo": "simplex-chat/simplexmq",
      "target": "Reproduce latest release",
      "target_type": "term"
    }
  ],
  "fetched_at": "2026-04-29T20:00:01.971424+00:00",
  "fetched_files": [
    {
      "path": "README.md",
      "size": 16939
    },
    {
      "path": "Dockerfile",
      "size": 2467
    },
    {
      "path": ".github/workflows/build.yml",
      "size": 8752
    },
    {
      "path": ".github/workflows/docker-image.yml",
      "size": 1593
    },
    {
      "path": ".github/workflows/reproduce-schedule.yml",
      "size": 1392
    }
  ],
  "related_repositories": [],
  "repo": {
    "archived": false,
    "default_branch": "stable",
    "description": "\u2699\ufe0f SimpleXMQ - A reference implementation of the SimpleX Messaging Protocol for simplex queues over public networks.",
    "fork": false,
    "full_name": "simplex-chat/simplexmq",
    "html_url": "https://github.com/simplex-chat/simplexmq",
    "language": "Haskell",
    "pushed_at": "2026-04-29T19:32:23Z",
    "stargazers_count": 785,
    "topics": [],
    "updated_at": "2026-04-20T00:23:32Z"
  },
  "repo_links": [
    {
      "edge_type": "explicit-github-link",
      "full_name": "mshekow/directory-checksum",
      "source_file": "Dockerfile"
    }
  ],
  "terms": [
    {
      "context_snippet": "build",
      "edge_type": "workflow-name",
      "source_file": ".github/workflows/build.yml",
      "term": "build"
    },
    {
      "context_snippet": "Reproduce latest release",
      "edge_type": "workflow-name",
      "source_file": ".github/workflows/reproduce-schedule.yml",
      "term": "Reproduce latest release"
    }
  ]
}
