{
  "edges": [
    {
      "edge_type": "package-json:dependencies",
      "source_file": "package.json",
      "source_repo": "holochain/hc-spin",
      "target": "@electron-toolkit/preload",
      "target_type": "component"
    },
    {
      "edge_type": "package-json:dependencies",
      "source_file": "package.json",
      "source_repo": "holochain/hc-spin",
      "target": "@electron-toolkit/utils",
      "target_type": "component"
    },
    {
      "edge_type": "package-json:dependencies",
      "source_file": "package.json",
      "source_repo": "holochain/hc-spin",
      "target": "@holochain/client",
      "target_type": "component"
    },
    {
      "edge_type": "package-json:dependencies",
      "source_file": "package.json",
      "source_repo": "holochain/hc-spin",
      "target": "@holochain/hc-spin-rust-utils",
      "target_type": "component"
    },
    {
      "edge_type": "package-json:dependencies",
      "source_file": "package.json",
      "source_repo": "holochain/hc-spin",
      "target": "@msgpack/msgpack",
      "target_type": "component"
    },
    {
      "edge_type": "package-json:dependencies",
      "source_file": "package.json",
      "source_repo": "holochain/hc-spin",
      "target": "bufferutil",
      "target_type": "component"
    },
    {
      "edge_type": "package-json:dependencies",
      "source_file": "package.json",
      "source_repo": "holochain/hc-spin",
      "target": "commander",
      "target_type": "component"
    },
    {
      "edge_type": "package-json:dependencies",
      "source_file": "package.json",
      "source_repo": "holochain/hc-spin",
      "target": "electron",
      "target_type": "component"
    },
    {
      "edge_type": "package-json:dependencies",
      "source_file": "package.json",
      "source_repo": "holochain/hc-spin",
      "target": "electron-context-menu",
      "target_type": "component"
    },
    {
      "edge_type": "package-json:dependencies",
      "source_file": "package.json",
      "source_repo": "holochain/hc-spin",
      "target": "get-port",
      "target_type": "component"
    },
    {
      "edge_type": "package-json:dependencies",
      "source_file": "package.json",
      "source_repo": "holochain/hc-spin",
      "target": "js-sha512",
      "target_type": "component"
    },
    {
      "edge_type": "package-json:dependencies",
      "source_file": "package.json",
      "source_repo": "holochain/hc-spin",
      "target": "nanoid",
      "target_type": "component"
    },
    {
      "edge_type": "package-json:dependencies",
      "source_file": "package.json",
      "source_repo": "holochain/hc-spin",
      "target": "split",
      "target_type": "component"
    },
    {
      "edge_type": "package-json:devDependencies",
      "source_file": "package.json",
      "source_repo": "holochain/hc-spin",
      "target": "@electron-toolkit/eslint-config-prettier",
      "target_type": "component"
    },
    {
      "edge_type": "package-json:devDependencies",
      "source_file": "package.json",
      "source_repo": "holochain/hc-spin",
      "target": "@electron-toolkit/eslint-config-ts",
      "target_type": "component"
    },
    {
      "edge_type": "package-json:devDependencies",
      "source_file": "package.json",
      "source_repo": "holochain/hc-spin",
      "target": "@electron-toolkit/tsconfig",
      "target_type": "component"
    },
    {
      "edge_type": "package-json:devDependencies",
      "source_file": "package.json",
      "source_repo": "holochain/hc-spin",
      "target": "@types/node",
      "target_type": "component"
    },
    {
      "edge_type": "package-json:devDependencies",
      "source_file": "package.json",
      "source_repo": "holochain/hc-spin",
      "target": "electron-builder",
      "target_type": "component"
    },
    {
      "edge_type": "package-json:devDependencies",
      "source_file": "package.json",
      "source_repo": "holochain/hc-spin",
      "target": "electron-vite",
      "target_type": "component"
    },
    {
      "edge_type": "package-json:devDependencies",
      "source_file": "package.json",
      "source_repo": "holochain/hc-spin",
      "target": "eslint",
      "target_type": "component"
    },
    {
      "edge_type": "package-json:devDependencies",
      "source_file": "package.json",
      "source_repo": "holochain/hc-spin",
      "target": "eslint-plugin-simple-import-sort",
      "target_type": "component"
    },
    {
      "edge_type": "package-json:devDependencies",
      "source_file": "package.json",
      "source_repo": "holochain/hc-spin",
      "target": "prettier",
      "target_type": "component"
    },
    {
      "edge_type": "package-json:devDependencies",
      "source_file": "package.json",
      "source_repo": "holochain/hc-spin",
      "target": "rimraf",
      "target_type": "component"
    },
    {
      "edge_type": "package-json:devDependencies",
      "source_file": "package.json",
      "source_repo": "holochain/hc-spin",
      "target": "typescript",
      "target_type": "component"
    },
    {
      "edge_type": "package-json:devDependencies",
      "source_file": "package.json",
      "source_repo": "holochain/hc-spin",
      "target": "utf-8-validate",
      "target_type": "component"
    },
    {
      "edge_type": "package-json:devDependencies",
      "source_file": "package.json",
      "source_repo": "holochain/hc-spin",
      "target": "vite",
      "target_type": "component"
    },
    {
      "edge_type": "workflow-uses",
      "source_file": ".github/workflows/test.yaml",
      "source_repo": "holochain/hc-spin",
      "target": "actions/checkout@v3",
      "target_type": "component"
    },
    {
      "edge_type": "workflow-uses",
      "source_file": ".github/workflows/test.yaml",
      "source_repo": "holochain/hc-spin",
      "target": "re-actors/alls-green@release/v1",
      "target_type": "component"
    },
    {
      "edge_type": "workflow-name",
      "source_file": ".github/workflows/test.yaml",
      "source_repo": "holochain/hc-spin",
      "target": "test",
      "target_type": "term"
    }
  ],
  "generated_at": "2026-05-02T18:23:34.576038+00:00",
  "source_repo": "holochain/hc-spin"
}
