{
  "ambiguity_status": "unresolved",
  "candidate_buckets": [
    "workflow-process",
    "data-document-artifact"
  ],
  "candidate_definition_hints": [
    {
      "source_kind": "repo-description",
      "status": "context-only",
      "text": "A pytorch quantization backend for optimum"
    },
    {
      "source_kind": "source-snippet",
      "status": "context-only",
      "text": "Linux CPU tests"
    }
  ],
  "candidate_glosses": [
    {
      "source_kind": "source-snippet",
      "status": "candidate",
      "text": "Linux CPU tests"
    }
  ],
  "candidate_primary_bucket": "workflow-process",
  "candidate_related_terms": [
    {
      "provider": "datamuse",
      "relation": "meaning-like",
      "score": 18519,
      "status": "candidate",
      "text": "unix"
    },
    {
      "provider": "datamuse",
      "relation": "meaning-like",
      "score": 18125,
      "status": "candidate",
      "text": "play"
    },
    {
      "provider": "datamuse",
      "relation": "meaning-like",
      "score": 18125,
      "status": "candidate",
      "text": "trap"
    },
    {
      "provider": "datamuse",
      "relation": "meaning-like",
      "score": 17830,
      "status": "candidate",
      "text": "print"
    },
    {
      "provider": "datamuse",
      "relation": "meaning-like",
      "score": 10395,
      "status": "candidate",
      "text": "beatrix"
    }
  ],
  "candidate_senses": [
    {
      "candidate_buckets": [
        "workflow-process",
        "data-document-artifact"
      ],
      "label": "Linux CPU tests",
      "sense_id": "linux-cpu-tests#sense-1",
      "status": "candidate"
    }
  ],
  "candidate_synonyms": [],
  "concept_id": "linux-cpu-tests",
  "definition_status": "unresolved",
  "discovered_via": "workflow-name",
  "gloss_status": "unresolved",
  "lexical_providers": [
    "datamuse"
  ],
  "lexical_status": "unresolved",
  "normalized_form": "linux-cpu-tests",
  "observation_id": "2ad2049cc3113dcc",
  "observation_kind": "workflow-name",
  "observed_at": "2026-05-05T18:38:09.351693+00:00",
  "observed_text": "Linux CPU tests",
  "source_context_snippet": "Linux CPU tests",
  "source_file": ".github/workflows/linux-cpu-tests.yml",
  "source_repo": "huggingface/optimum-quanto",
  "source_repo_description": "A pytorch quantization backend for optimum"
}
