{
  "ambiguity_status": "unresolved",
  "candidate_buckets": [
    "tool-component",
    "capability"
  ],
  "candidate_definition_hints": [
    {
      "source_kind": "repo-description",
      "status": "context-only",
      "text": "Cross-platform asynchronous I/O"
    },
    {
      "source_kind": "source-snippet",
      "status": "context-only",
      "text": "![libuv][libuv_banner]"
    }
  ],
  "candidate_glosses": [
    {
      "source_kind": "source-snippet",
      "status": "candidate",
      "text": "![libuv][libuv_banner]"
    }
  ],
  "candidate_primary_bucket": "tool-component",
  "candidate_related_terms": [
    {
      "provider": "datamuse",
      "relation": "meaning-like",
      "score": 39936748,
      "status": "candidate",
      "text": "unsynchronized"
    },
    {
      "provider": "datamuse",
      "relation": "meaning-like",
      "score": 39936426,
      "status": "candidate",
      "text": "unsynchronous"
    },
    {
      "provider": "datamuse",
      "relation": "meaning-like",
      "score": 39935095,
      "status": "candidate",
      "text": "nonsynchronous"
    },
    {
      "provider": "datamuse",
      "relation": "meaning-like",
      "score": 39932657,
      "status": "candidate",
      "text": "nonparallel"
    },
    {
      "provider": "datamuse",
      "relation": "meaning-like",
      "score": 39912568,
      "status": "candidate",
      "text": "anachronic"
    }
  ],
  "candidate_senses": [
    {
      "candidate_buckets": [
        "tool-component",
        "capability"
      ],
      "label": "asynchronous",
      "sense_id": "asynchronous#sense-1",
      "status": "candidate"
    }
  ],
  "candidate_synonyms": [
    {
      "provider": "datamuse",
      "relation": "synonym",
      "score": 5046,
      "status": "candidate",
      "text": "serial"
    },
    {
      "provider": "datamuse",
      "relation": "synonym",
      "score": 4028,
      "status": "candidate",
      "text": "anachronistic"
    },
    {
      "provider": "datamuse",
      "relation": "synonym",
      "score": 3021,
      "status": "candidate",
      "text": "anachronic"
    },
    {
      "provider": "datamuse",
      "relation": "synonym",
      "score": 1015,
      "status": "candidate",
      "text": "nonsynchronous"
    },
    {
      "provider": "datamuse",
      "relation": "synonym",
      "score": 1011,
      "status": "candidate",
      "text": "allochronic"
    }
  ],
  "concept_id": "asynchronous",
  "definition_status": "unresolved",
  "discovered_via": "repo-topic",
  "gloss_status": "unresolved",
  "lexical_providers": [
    "datamuse"
  ],
  "lexical_status": "unresolved",
  "normalized_form": "asynchronous",
  "observation_id": "f99f553658478c1d",
  "observation_kind": "repo-topic",
  "observed_at": "2026-04-30T00:37:16.824464+00:00",
  "observed_text": "asynchronous",
  "source_context_snippet": "![libuv][libuv_banner]",
  "source_file": null,
  "source_repo": "libuv/libuv",
  "source_repo_description": "Cross-platform asynchronous I/O"
}
